arg/__init__.py
arg/core.py
arg/tests/__init__.py
arg/tests/test_core.py
python_args-1.0.2.dist-info/LICENSE
python_args-1.0.2.dist-info/WHEEL
python_args-1.0.2.dist-info/METADATA
python_args-1.0.2.dist-info/RECORD
